snips_nlu_ontology/__version__
snips_nlu_ontology/builtin_entity_parser.py
snips_nlu_ontology/__init__.py
snips_nlu_ontology/builtin_entities.py
snips_nlu_ontology/gazetteer_entity_parser.py
snips_nlu_ontology/utils.py
snips_nlu_ontology/dylib/.gitignore
snips_nlu_ontology/dylib/libsnips_nlu_ontology_rs.cpython-34m.so
snips_nlu_ontology-0.62.0.dist-info/metadata.json
snips_nlu_ontology-0.62.0.dist-info/WHEEL
snips_nlu_ontology-0.62.0.dist-info/top_level.txt
snips_nlu_ontology-0.62.0.dist-info/DESCRIPTION.rst
snips_nlu_ontology-0.62.0.dist-info/RECORD
snips_nlu_ontology-0.62.0.dist-info/METADATA
