Metadata-Version: 2.0
Name: snips-nlu-ontology
Version: 0.62.0
Summary: Python wrapper of the Snips NLU ontology
Home-page: UNKNOWN
Author: Kevin Lefevre, Adrien Ball
Author-email: kevin.lefevre@snips.ai, adrien.ball@snips.ai
License: Apache 2.0
Platform: UNKNOWN
Classifier: Programming Language :: Python :: 2
Classifier: Programming Language :: Python :: 2.7
Classifier: Programming Language :: Python :: 3
Classifier: Programming Language :: Python :: 3.4
Classifier: Programming Language :: Python :: 3.5
Classifier: Programming Language :: Python :: 3.6
Requires-Dist: future (==0.16.0)
Requires-Dist: wheel (==0.30.0)
Requires-Dist: pathlib (==1.0.1); python_version < "3.4"
